dockerwrapper/__init__.py
dockerwrapper/__version__.py
dockerwrapper/core.py
dockerwrapper/exceptions.py
tl_dockerwrapper-1.3.5.dist-info/LICENSE
tl_dockerwrapper-1.3.5.dist-info/METADATA
tl_dockerwrapper-1.3.5.dist-info/WHEEL
tl_dockerwrapper-1.3.5.dist-info/top_level.txt
tl_dockerwrapper-1.3.5.dist-info/RECORD
