Metadata-Version: 2.1
Name: tl-dockerwrapper
Version: 1.3.5
Summary: Simple wrapper for Docker SDKs
Home-page: https://github.com/thanhledev/dockerwrapper
Author: Thanh Le
Author-email: thanhledev@gmail.com
License: MIT
Platform: UNKNOWN
Classifier: License :: OSI Approved :: MIT License
Classifier: Programming Language :: Python
Classifier: Programming Language :: Python :: 3
Classifier: Programming Language :: Python :: 3.6
Requires-Python: >=3.6.0
Requires-Dist: docker
Requires-Dist: tl-utilities
